pybkash/__init__.py
pybkash/exception_handlers.py
pybkash/exceptions.py
pybkash/main.py
pybkash/models.py
pybkash/token_manager.py
pybkash-0.2.1.dist-info/licenses/LICENSE
pybkash-0.2.1.dist-info/WHEEL
pybkash-0.2.1.dist-info/METADATA
pybkash-0.2.1.dist-info/RECORD
