Metadata-Version: 2.4
Name: pybkash
Version: 0.2.1
Summary: A Pythonic client for the bKash payment gateway. Supports both synchronous and asynchronous usage and covers the entire API surface.
Keywords: bkash,payments,fintech,api,bangladesh
Author: Monazir Muhammad Doha
Author-email: Monazir Muhammad Doha <mmdoha@houndsec.net>
License-Expression: MIT
License-File: LICENSE
Classifier: Programming Language :: Python :: 3
Classifier: Operating System :: OS Independent
Requires-Dist: httpx>=0.27.0
Requires-Python: >=3.9
Project-URL: Homepage, https://github.com/itsmmdoha/pybkash
Project-URL: Issues, https://github.com/itsmmdoha/pybkash/issues
